webhook_server/__init__.py
webhook_server/datadog.py
webhook_server/webhooks.py
webhook_server-0.1.3.dist-info/METADATA
webhook_server-0.1.3.dist-info/WHEEL
webhook_server-0.1.3.dist-info/RECORD
