Metadata-Version: 2.1
Name: webhook_server
Version: 0.1.3
Summary: Create a webhook server with Flask to forward Datadog alerts to Telegram
Home-page: https://gitlab.com/daisukixci/webhook_server
License: MIT
Keywords: datadog,webhook,telegram
Author: daisukixci
Author-email: daisuki@tuxtrooper.com
Maintainer: daisukixci
Maintainer-email: daisuki@tuxtrooper.com
Requires-Python: >=3.10,<4.0
Classifier: License :: OSI Approved :: MIT License
Classifier: Programming Language :: Python :: 3
Classifier: Programming Language :: Python :: 3.10
Classifier: Programming Language :: Python :: 3.11
Classifier: Programming Language :: Python :: 3.12
Requires-Dist: Flask (>=3.0.3,<4.0.0)
Requires-Dist: Flask-BasicAuth (>=0.2.0,<0.3.0)
Requires-Dist: Flask-HTTPAuth (>=4.8.0,<5.0.0)
Requires-Dist: requests (>=2.32.3,<3.0.0)
Project-URL: Documentation, https://gitlab.com/daisukixci/webhook_server/-/blob/main/README.md
Project-URL: Repository, https://gitlab.com/daisukixci/webhook_server
